{"module":"Module-07-Pipeline-Review-Forecasting","content_type":"learner_pack","timestamp":"2026-02-18T05:32:05.040Z","sections":{"worksheets":[{"number":"1.1","title":"Map Your Team's Pipeline by Stage","content":"**Objective:** Visualize your team's pipeline distribution and identify gaps.\n**Instructions:** Fill in the data for your team. Use deal count and total value by stage.\n```\nSTAGE               | DEAL COUNT | TOTAL VALUE | AVG DEAL SIZE | % OF PIPELINE\nProspect            |     ___    |    $____    |     $____     |      ___%\nDiscovery           |     ___    |    $____    |     $____     |      ___%\nQualification       |     ___    |    $____    |     $____     |      ___%\nAdvanced            |     ___    |    $____    |     $____     |      ___%\nClosed (Won/Lost)   |     ___    |    $____    |     $____     |      ___%\n|            |            |               |\nTOTAL               |     ___    |    $____    |     $____     |     100%\n```\n**Reflection Questions:**\n1. What stage has the most deals? What stage has the most value?\n2. Is the distribution healthy (multiple stages represented)?\n3. Are deals moving smoothly from stage to stage, or stuck anywhere?\n---"},{"number":"1.2","title":"What Does the Shape Tell You?","content":"**Objective:** Interpret your pipeline shape and identify coaching opportunities.\n**Instructions:** Describe your pipeline shape and what it suggests.\n**My Pipeline Shape:**\n- Early-stage (Prospect + Discovery) is __% of total. Is this healthy? ___\n- Middle-stage (Qualification) is __% of total. Is this healthy? ___\n- Late-stage (Advanced) is __% of total. Is this healthy? ___\n**What I See:**\n- Strength: ____________________________________________\n- Gap: ____________________________________________\n- Coaching Needed: ____________________________________\n**Example Patterns (Check the ones that apply):**\n- [ ] Too many early-stage deals (> 50% in Prospect + Discovery)\n- **What it means:** Qualification problem. Deals not moving forward.\n- **Coaching:** \"Walk me through how you qualify. What questions do you ask before moving to Qualification?\"\n- [ ] Deals stuck in middle (same deals in Qualification for 3+ weeks)\n- **What it means:** Momentum problem. Rep not pushing or buyer stalled.\n- **Coaching:** \"What's the next step? When are you talking to them next?\"\n- [ ] Very few deals in Advanced\n- **What it means:** Pipeline maturity problem. Not enough deals far along.\n- **Coaching:** \"How long does a typical deal stay in Qualification before advancing?\"\n- [ ] Few early-stage deals\n- **What it means:** Prospecting problem. Pipeline will dry up.\n- **Coaching:** \"What's your prospecting plan? How many new deals do you need in Prospect each week?\"\n---\n## SUB-MODULE 2: THE CONVERSION RATE & MATH"},{"number":"2.1","title":"Calculate Your Company Conversion Rate","content":"**Objective:** Find your actual close rate from historical data.\n**Instructions:** Gather data from the last 12 months of closed deals (won and lost).\n```\nCONVERSION RATE CALCULATION\nLast 12 months of closed deals:\n- Total deals closed (won + lost):     _____\n- Total deals closed WON:              _____\n- Total deals closed LOST:             _____\nOverall Close Rate = Deals Won ÷ Total Closed\n= _____ ÷ _____ = _____%\nExample: 48 won ÷ 60 total = 80%\n```\n**Stage-by-Stage Breakdown (Optional but Recommended):**\n```\nSTAGE                    | DEALS IN STAGE | ADVANCED/CLOSED | CONVERSION %\nProspect → Discovery     |      _____     |      _____      |     ____%\nDiscovery → Qualified    |      _____     |      _____      |     ____%\nQualified → Advanced     |      _____     |      _____      |     ____%\nAdvanced → Closed (Won)  |      _____     |      _____      |     ____%\nOverall (Prospect → Won) |      _____     |      _____      |     ____%\n```\n**Reflection Questions:**\n1. Is your overall close rate higher, lower, or in line with industry norms (SaaS 60-80%, Real Estate 40-60%)?\n2. Where is your biggest drop-off (where do you lose the most deals)?\n3. Has this rate been stable, or is it trending up or down?\n---"},{"number":"2.2","title":"Calculate Each Rep's Conversion Rate & Compare","content":"**Objective:** Identify high and low performers and spot coaching opportunities.\n**Instructions:** Calculate each rep's close rate from last 12 months. Compare to company average.\n```\nREP NAME        | WON DEALS | LOST DEALS | CLOSE RATE | vs COMPANY AVG | GAP | STATUS\n____________    |    ___    |    ___     |   ____%    |      ____%     | ___ | ______\n____________    |    ___    |    ___     |   ____%    |      ____%     | ___ | ______\n____________    |    ___    |    ___     |   ____%    |      ____%     | ___ | ______\n____________    |    ___    |    ___     |   ____%    |      ____%     | ___ | ______\n|           |            |            |                |     |\nCompany Average |    ___    |    ___     |   ____%    |        —       | —   |\n```\n**Example:**\n```\nSarah       | 12 | 3  | 80%  | vs 75% | +5%  | Exceeding\nMarcus      | 8  | 8  | 50%  | vs 75% | -25% | Below Average (Coaching)\nJamie       | 10 | 5  | 67%  | vs 75% | -8%  | Slightly Below\nCompany Avg | 48 | 12 | 75%  |        |      |\n```\n**Analysis:**\n- **Above Average** (company rate + 5% or more):\n- Rep Name: ____________\n- Why? (better qualification? better sales skills? better territory?)\n- Action: Replicate their process with other reps.\n- **Below Average** (company rate - 5% or more):\n- Rep Name: ____________\n- Why? (weaker qualification? sales skills gap? territory issue?)\n- Action: Coaching conversation needed. See coaching template in Sub-Module 5.\n---\n## SUB-MODULE 3: THE ACCURATE FORECAST"},{"number":"3.1","title":"Build Your Forecast: Pipeline, Conversion, Number","content":"**Objective:** Calculate your base forecast using data.\n**Instructions:** Take your qualified pipeline and apply your conversion rate.\n```\nYOUR FORECAST CALCULATION\nStep 1: Identify Qualified Pipeline\n- Deals in Qualification: $__________\n- Deals in Advanced:      $__________\n- Total Qualified:        $__________\nStep 2: Apply Your Conversion Rate\n- Your Historical Close Rate (from Worksheet 2.1): ____%\nStep 3: Calculate Base Forecast\n- Base Forecast = Qualified Pipeline × Conversion Rate\n- $_________ × ___% = $__________\nExample:\n- Qualified Pipeline: $500K\n- Close Rate: 70%\n- Base Forecast: $500K × 70% = $350K\n```\n**For Each Rep:**\n```\nREP: ________________\nQualified Pipeline (Qual + Advanced):     $__________\nRep's Close Rate (from Worksheet 2.2):    ____%\nBase Forecast = $ × __ % =                $__________\n```\n**Reflection:**\n1. Is this forecast higher, lower, or similar to what you guessed before?\n2. Does this feel achievable based on deal movement?\n---"},{"number":"3.2","title":"Scenarios and Confidence Assessment","content":"**Objective:** Assess upside, downside, and your confidence in the forecast.\n**Instructions:** For your base forecast, identify what could go right and wrong.\n```\nFORECAST ASSESSMENT\nBase Forecast (Math): $__________\nUPSIDE SCENARIO: What Could Accelerate?\n- Deal/Opportunity: _________________________ | Value: $_______ | Confidence: ___%\n- Deal/Opportunity: _________________________ | Value: $_______ | Confidence: ___%\n- Deal/Opportunity: _________________________ | Value: $_______ | Confidence: ___%\nTotal Upside (weighted): $__________\nUpside Forecast (Base + Upside): $__________\nDOWNSIDE SCENARIO: What Could Delay or Stall?\n- Deal/Opportunity: _________________________ | Value: $_______ | Impact: ___%\n- Deal/Opportunity: _________________________ | Value: $_______ | Impact: ___%\n- Deal/Opportunity: _________________________ | Value: $_______ | Impact: ___%\nTotal Downside (weighted): $__________\nDownside Forecast (Base - Downside): $__________\nYOUR CONFIDENCE ASSESSMENT:\n- Confidence in Base Forecast: ___%\n- Likely to exceed: __%\n- Likely to miss: __%\nExample:\n- Base: $350K | Confidence: 75%\n- 15% chance I hit $400K+ (upside)\n- 10% chance I hit below $300K (downside)\n```\n**Reflection:**\n1. Where is your biggest upside? Is it achievable?\n2. Where is your biggest downside? Can you mitigate it?\n3. Are you confident in this forecast, or is there uncertainty?\n---\n## SUB-MODULE 4: THE WEEKLY PIPELINE REVIEW"},{"number":"4.1","title":"Design Your Weekly Review Template","content":"**Objective:** Create a template for your weekly pipeline review meeting.\n**Instructions:** Customize the agenda below for your team.\n```\nWEEKLY PIPELINE REVIEW AGENDA\nDuration: 30 minutes\nFrequency: Every [DAY OF WEEK] at [TIME]\nAttendees: [REPS], [YOU]\n1. OVERALL PIPELINE HEALTH [3 min]\n- This Week Total: $________\n- Last Week Total: $________\n- Plan for This Week: $________\n- On Pace? Yes / No / Close\n- Key Changes: ___________________________________________\n2. BY STAGE BREAKDOWN [5 min]\n- Prospect: $ _______ ( __ deals)\n- Discovery: $ _______ ( __ deals)\n- Qualification: $ _______ ( __ deals)\n- Advanced: $ _______ ( __ deals)\n- Notes: __________________________________________________\n3. CONVERSION RATES [4 min]\n- Rates for last 4 weeks (vs 12-month average):\n- Rep: ___% (avg ___%)\n- Rep: ___% (avg ___%)\n- Rep: ___% (avg ___%)\n- Anyone above or below average? __________________________\n4. BIG DEALS AT RISK [4 min]\n- Deal > __ days in stage / Deal with past close date:\n- Deal Name: _________ | Value: $ _____ | Days: ___ | Blocker: _______\n- Deal Name: _________ | Value: $ _____ | Days: ___ | Blocker: _______\n- Action Items: ___________________________________________\n5. NEW & DISQUALIFIED [2 min]\n- New deals entered (week): ___ deals, $______\n- Disqualified (week): ___ deals, Reasons: __________________\n- Net pipeline growth: ______________________________________\n6. FORECAST THIS WEEK [2 min]\n- Expected closes: $________\n- On pace for plan? Yes / No\n- Anything blocking a close? ________________________________\n7. COACHING MOMENT [5 min]\n- Rep needing coaching: ____________________________________\n- Topic: ___________________________________________________\n- Follow-up 1-on-1 scheduled? Yes / No | When: _____________\nNotes: _____________________________________________________\n```\n---"},{"number":"4.2","title":"This Week's Coaching Opportunities from Pipeline","content":"**Objective:** Use pipeline data to identify specific coaching needs.\n**Instructions:** Based on your pipeline review, what rep needs coaching and why?\n```\nCOACHING OPPORTUNITY #1\nRep Name: ____________________________\nPipeline Pattern I Noticed: _________________________________\nExample (deal name/situation): ______________________________\nCoaching Topic:\n[ ] Qualification gap (taking deals too early)\n[ ] Stuck deal (not pushing forward)\n[ ] Cycle time issue (moving too fast or too slow)\n[ ] Deal size issue (too small/large)\n[ ] Conversion rate drop (more losses than usual)\n[ ] Other: _________________________________________________\nCoaching Question I'll Ask:\n\"_________________________________________________________?\"\nExpected Outcome:\n\"If this rep [addresses issue], then [result] will improve.\"\nCOACHING OPPORTUNITY #2\nRep Name: ____________________________\n[Same format as above]\n```\n---\n## SUB-MODULE 5: PIPELINE COACHING IN PRACTICE"},{"number":"5.1","title":"One Rep's Pipeline Challenges","content":"**Objective:** Diagnose coaching needs for a single rep.\n**Instructions:** Pick one rep. Analyze their pipeline and identify gaps.\n```\nREP NAME: ____________________________\nTHEIR PIPELINE BREAKDOWN:\n- Prospect: ___% of total pipeline\n- Discovery: ___% of total pipeline\n- Qualification: ___% of total pipeline\n- Advanced: ___% of total pipeline\nPIPELINE SHAPE ASSESSMENT:\nIs it healthy? [ ] Yes [ ] No [ ] Partly\nIf not healthy, what's the problem?\n[ ] Too many early-stage deals (poor qualification)\n[ ] Deals stuck in middle (momentum issue)\n[ ] Very few deals in Advanced (pipeline maturity issue)\n[ ] Deals too small (deal sizing issue)\n[ ] Other: _________________________________________________\nCONVERSION RATE:\nRep's close rate: _____ %\nCompany average: _____ %\nDifference: _____ % (Above / Below)\nIs the rate healthy?\n[ ] Yes, at or above average\n[ ] No, below average; needs coaching\nSTUCK DEALS (if any):\n- Deal Name: _____________ | Days in Stage: ___ | Blocker: __________\n- Deal Name: _____________ | Days in Stage: ___ | Blocker: __________\nCOACHING PRIORITY:\nWhat is the ONE biggest coaching opportunity for this rep?\n_____________________________________________________________\nWhy does it matter?\n\"If this rep [improves in this area], their [rate/cycle/pipeline] will improve by ___.\"\n```\n---"},{"number":"5.2","title":"Coach the Conversation Script","content":"**Objective:** Practice the coaching conversation.\n**Instructions:** Write out the conversation you'll have with this rep.\n```\nCOACHING CONVERSATION SCRIPT\nRep: ____________________________\nTopic: __________________________\nYOUR OPENING (Curiosity, not criticism):\n\"I want to talk about [topic]. I noticed [pattern].\nHelp me understand what's going on.\"\nRep Response: __________________________________________\nYOUR QUESTION (Help them see the gap):\n\"When you [action], do you [ask/check/do]?\"\nRep Response: __________________________________________\nYOUR TEACHING (Name the gap):\n\"Here's what I'm seeing: [pattern] suggests [root cause].\nWhat would happen if instead you [better behavior]?\"\nRep Response: __________________________________________\nYOUR ASK (Specific action):\n\"Here's what I'd like: For your next [X deals/timeframe],\n[specific action]. Let's see if that changes [outcome].\"\nRep Response: __________________________________________\nYOUR ACCOUNTABILITY (Check-in):\n\"Let's check in [day/date] and see how it's going.\nSound fair?\"\nRep Response: __________________________________________\n```\n**After the Conversation:**\n- Did the rep understand the gap?    [ ] Yes [ ] No\n- Did they agree to the action?       [ ] Yes [ ] No\n- Follow-up scheduled?                [ ] Yes [ ] No | Date: ________\n---\n# PART B: SELF-ASSESSMENT TOOLS"}],"assessments":[{"number":"1","title":"Pipeline Health Audit","content":"**Objective:** Diagnose whether your team's pipeline is healthy.\n**Instructions:** Answer each question. Score as indicated. Sum your total.\n```\nPIPELINE HEALTH AUDIT\nSTAGE 1: OVERALL DISTRIBUTION\n___ 1. Do you have deals in all five stages (Prospect through Advanced)?\n[ ] Yes (2 pts) [ ] No (0 pts)\n___ 2. Is your Prospect+Discovery stage 30-50% of total pipeline?\n[ ] Yes, healthy (2 pts)\n[ ] Too much (>50%) (1 pt)\n[ ] Too little (<30%) (0 pts)\n___ 3. Is your Advanced stage 15-25% of total pipeline?\n[ ] Yes, healthy (2 pts)\n[ ] Too little (<15%) (0 pts)\nSTAGE 2: DEAL MOVEMENT\n___ 4. Are deals moving from stage to stage at expected pace?\n(Prospect/Discovery 7-14 days; Qual 10-21 days; Advanced 5-10 days)\n[ ] Yes, moving smoothly (2 pts)\n[ ] Some deals stuck (1 pt)\n[ ] Many deals stuck (0 pts)\n___ 5. Do you have deals stuck in a stage >50% beyond expected duration?\n[ ] No (2 pts)\n[ ] Yes, 1-2 deals (1 pt)\n[ ] Yes, multiple deals (0 pts)\nSTAGE 3: DEAL SIZE & DISTRIBUTION\n___ 6. Is your pipeline distributed across deal sizes?\n(Not dependent on one massive deal)\n[ ] Yes, balanced (2 pts)\n[ ] Somewhat concentrated (1 pt)\n[ ] Yes, too dependent on one deal (0 pts)\n___ 7. Is your average deal size consistent with your quota/goal?\n[ ] Yes (2 pts)\n[ ] Below target (1 pt)\n[ ] Way below target (0 pts)\nSTAGE 4: CONVERSION RATE\n___ 8. Do you know your team's historical close rate?\n[ ] Yes, calculated from 12 months (2 pts)\n[ ] Yes, rough estimate (1 pt)\n[ ] No (0 pts)\n___ 9. Is your close rate healthy (60%+ for SaaS, 40%+ for RE)?\n[ ] Yes, above target (2 pts)\n[ ] Yes, at target (2 pts)\n[ ] No, below target (0 pts)\nSTAGE 5: REP-BY-REP HEALTH\n___ 10. Do you track conversion rate by rep?\n[ ] Yes, weekly (2 pts)\n[ ] Yes, monthly (1 pt)\n[ ] No (0 pts)\nTOTAL SCORE: _____ / 20\nSCORING:\n18-20: Green (Healthy pipeline, managing by data)\n14-17: Yellow (Good but could tighten; some risks)\n10-13: Red (Pipeline issues need addressing)\n<10:   Crisis (Major coaching needed)\nMY PIPELINE HEALTH: __________________________________________\nTop Priority to Improve: _________________________________________\n```\n---","rubric":null},{"number":"2","title":"Forecast Confidence","content":"**Objective:** Evaluate whether you can back up your forecast with data.\n**Instructions:** Answer honestly. Check the ones that apply.\n```\nFORECAST CONFIDENCE ASSESSMENT\nCAN I DEFEND MY FORECAST TO LEADERSHIP?\n[ ] I can clearly state my qualified pipeline ($________)\n[ ] I can clearly state my historical close rate (___%)\n[ ] I can calculate: Pipeline × Rate = Forecast ($________)\n[ ] I can name deals that could come in early (upside scenario)\n[ ] I can name deals that could be at risk (downside scenario)\n[ ] I can state my confidence level (I am ___% confident)\n[ ] I have not sandbag'd my forecast (am I honestly forecasting?)\n[ ] I have not hype'd my forecast (am I wishful thinking?)\n[ ] I can walk leadership through the math\n[ ] I can explain what could change the forecast\nIF I CHECKED <7 BOXES:\nYour forecast confidence is LOW. Work on these areas:\n1. Know your pipeline number (Worksheet 3.1)\n2. Know your conversion rate (Worksheet 2.1)\n3. Identify scenarios (Worksheet 3.2)\n4. Practice defending it aloud\nIF I CHECKED 7-9 BOXES:\nYour forecast confidence is MEDIUM. You're close. Make sure you:\n1. Have scenarios identified\n2. Can explain why you're confident or uncertain\n3. Have tracked forecast accuracy (were you right last month?)\nIF I CHECKED 10 BOXES:\nYour forecast confidence is HIGH. You're managing by data.\nContinue this. Track your accuracy. Celebrate wins.\n```\n---","rubric":null},{"number":"3","title":"Conversion Rate Reality","content":"**Objective:** Confirm you're using real conversion data, not guessing.\n**Instructions:** Calculate or estimate. Be honest about what you know.\n```\nCONVERSION RATE REALITY CHECK\nMY OVERALL CONVERSION RATE:\nWhat is your company's actual close rate (last 12 months)?\n_________% (I calculated this / I'm estimating)\nBY REP:\n[ ] I know each rep's close rate from actual data\n[ ] I know some reps' rates but not all\n[ ] I don't really know individual rates\nBY STAGE:\n[ ] I know conversion rate by stage (Prospect→Discovery, etc.)\n[ ] I know overall rate but not by stage\n[ ] I don't track this\nTRENDS:\n[ ] My close rate is trending up\n[ ] My close rate is stable\n[ ] My close rate is trending down\n[ ] I'm not sure; I don't track trends\nCOACHING IMPLICATIONS:\n[ ] I've identified reps below average and am coaching them\n[ ] I've identified reps above average and am learning from them\n[ ] I haven't analyzed performance by rep\n[ ] I don't discuss conversion rates with reps\nACCURACY:\nIf I was forecasting 12 months ago, how accurate was I?\nWithin 5%: [ ] Within 10%: [ ] Within 20%: [ ] Total guess: [ ]\nREALITY CHECK:\nAre you managing conversion rates, or hoping they stay the same?\n[ ] Managing (I track, coach, celebrate improvements)\n[ ] Hoping (I don't really check it)\nNEXT STEP:\nIf you're \"hoping,\" calculate your rate this week using Worksheet 2.1.\nThen calculate each rep's rate. Then coach.\n```\n---","rubric":null},{"number":"4","title":"Review Readiness","content":"**Objective:** Check if you're ready to run an effective weekly pipeline review.\n**Instructions:** Rate yourself on each item (1=not ready, 5=very ready). Sum the total.\n```\nWEEKLY REVIEW READINESS CHECKLIST\nSTRUCTURE:\n___ I have a set time for weekly review (same day/time)\n___ I have a standard agenda (not winging it)\n___ I keep it to 30 minutes\n___ I prep pipeline data before the meeting\nDATA:\n___ I know my total pipeline value\n___ I can break it down by stage\n___ I can name my team's close rate\n___ I know each rep's recent conversion rate\nMEETINGS:\n___ I run the meeting with discipline (stick to agenda)\n___ I surface one coaching opportunity per meeting\n___ I schedule 1-on-1s to follow up on coaching\n___ I close the meeting with next week's forecast\nOUTCOMES:\n___ Reps know their close rates\n___ Reps understand pipeline patterns\n___ Reps expect to be coached weekly\n___ Forecast accuracy is improving\nSCORING (each rated 1-5):\nTotal: _____ / 20\n15-20: Ready (Run your review this week)\n10-14: Almost Ready (Fix 1-2 areas; then start)\n5-9:   Not Yet (Do worksheets 4.1 & 4.2 first)\nMY READINESS: _____ / 20\nTop Area to Strengthen Before First Review:\n__________________________________________________________\n```\n---\n# PART C: ROLE-PLAY SCENARIOS\n## Scenario 1: Reading a Pipeline\n**Setting:** You're reviewing one rep's pipeline for the first time.\n**Context:**\n```\nRep: Sarah\nDays in Module: 3 months\nPipeline Summary:\n- Prospect: 5 deals, $75K total\n- Discovery: 8 deals, $150K total\n- Qualification: 15 deals, $350K total (some for 30+ days)\n- Advanced: 2 deals, $80K total\n- Total Pipeline: 30 deals, $655K\nSarah's Close Rate (12 months): 75%\nCompany Average: 75%\n```\n**Your Task:** What do you see? What's your coaching?\n**Debrief Questions:**\n1. What pattern stands out to you in Sarah's pipeline?\n2. Is her pipeline healthy or at risk?\n3. What's the one coaching question you'd ask?\n4. What would you expect to happen if she took your coaching?\n**Sample Answer:**\n1. Sarah's pipeline is heavy in Qualification (15/30 deals = 50%). Some are stuck (30+ days).\n2. At risk. Qualification deals aren't moving to Advanced.\n3. \"Some of your Qualification deals have been in that stage for more than a month. What's typical for you? What's blocking progression?\"\n4. If coached on moving deals faster or qualifying harder, Advanced would grow, close rate might stay at 75%, but cycle time would drop.\n---\n## Scenario 2: Forecasting to Leadership\n**Setting:** Quarterly forecast call with your VP Sales.\n**Context:**\n```\nYou are: A Sales Manager\nYour team's qualified pipeline: $1.2M\nYour team's close rate: 68% (12 months)\nDeals at risk: $150K (buyer budgets held up)\nPotential upside: $100K (two deals in Advanced moving fast)\nTiming: Two reps are out on vacation next week (covers 10% of pipeline)\n```\n**Your Task:** Make your forecast and defend it.\n**The Conversation:**\n- VP asks: \"What's your forecast for the quarter?\"\n- You need to provide: Base number, upside, downside, confidence level, reasoning\n**Debrief Questions:**\n1. What's your base forecast number and how did you calculate it?\n2. What's your upside scenario? How confident are you in it?\n3. What's your downside scenario? Why might it happen?\n4. What's your confidence level (0-100%)? Why?\n5. What could change the forecast between now and quarter-end?\n**Sample Answer:**\n1. Base: $1.2M × 68% = $816K. That's what the math says.\n2. Upside: Two Advanced deals ($100K) moving fast = $100K extra. 60% confident. Total upside: $876K.\n3. Downside: Buyer budgets at risk ($150K) slip, + vacation overlap ($50K) = $200K risk. Total downside: $616K.\n4. Confidence: 75% on the $816K number. 15% I'm higher, 10% I'm lower.\n5. If deals move as expected, I'll be at $876K. If they don't, I'll flag it by month 2.\n---\n## Scenario 3: Stuck Deal Coaching\n**Setting:** Weekly review meeting. You notice a deal stuck in Advanced.\n**Context:**\n```\nDeal: Acme Corp\nStage: Advanced (14 days)\nValue: $75K\nExpected Close Date: \"This week\"\nLast Rep Activity: Sent follow-up email 3 days ago\nBuyer Status: Waiting on their legal team's contract review\n```\n**Your Task:** Coach the rep to unstick the deal.\n**The Conversation Setup:**\n- Rep says: \"Yeah, they're just slow on legal.\"\n- You respond with: A question to help them see the gap\n**Debrief Questions:**\n1. What's the rep's gap? (Are they pushing hard enough? Do they have a timeline?)\n2. What question would you ask to help them see it?\n3. What's your specific coaching action?\n4. How will you know if it worked?\n**Sample Answer:**\n1. The rep is hoping, not pushing. They don't have a timeline from the buyer.\n2. \"When did you last talk to legal? What's their actual timeline—not hope, but actual?\"\n3. \"Today, call legal directly. Get a specific day they'll finish. If it's this week, great. If it's next week, that's a miss. Report back tonight.\"\n4. Deal closes by promised date OR is flagged as downside risk within 24 hours.\n---\n## Scenario 4: Low Conversion Rep Coaching\n**Setting:** You're coaching Marcus, whose close rate is 55% (vs team average 75%).\n**Context:**\n```\nRep: Marcus\n4-Week Close Rate: 55%\n12-Month Close Rate: 50%\nTrend: Not improving\nRecent Losses: TechCo, WidgetCorp, BuildCo\nReason for Losses: \"They chose a competitor\" / \"Timing wasn't right\" / \"Budget wasn't there\"\n```\n**Your Task:** Coach Marcus on why his rate is low.\n**The Conversation Setup:**\n- Marcus says: \"I'm in good deals, but the market is tough.\"\n- You respond with: A question to help him see the pattern\n**Debrief Questions:**\n1. What pattern do you see in Marcus's losses?\n2. Is this a qualification problem, a sales skills problem, or something else?\n3. What one question would you ask to help him see it?\n4. What specific coaching action would you give?\n**Sample Answer:**\n1. Pattern: He's losing on competitor and timing/budget—suggesting he's not qualifying tightly before going deep.\n2. Qualification. He's taking deals that don't have confirmed timeline or clear budget.\n3. \"When TechCo chose a competitor, did you know they were looking at other vendors before the end? Could you have known in Qualification?\"\n4. \"For your next 5 deals in Qualification, ask: Who else are you talking to? When do you expect to decide? Is budget actually approved? Don't move to Advanced until both are clear.\"\n---\n## Scenario 5: Forecast Miss Debrief\n**Setting:** End of quarter. You forecasted $800K. You closed $650K. VP asks for a debrief.\n**Context:**\n```\nForecast: $800K\nActual: $650K\nMiss: $150K (off by 19%)\nWhat Happened:\n- Two deals slipped to next quarter ($100K)\n- One deal was lost to competitor ($25K)\n- One deal disqualified (no real budget) ($25K)\n```\n**Your Task:** Explain what happened and what you learned.\n**The Conversation Setup:**\n- VP asks: \"Walk me through the miss.\"\n- You need to: Explain what happened, own it, and say what you'll do differently\n**Debrief Questions:**\n1. Which deal slip was predictable and which wasn't?\n2. What should you have flagged earlier?\n3. What coaching could have prevented this?\n4. What will you do differently next quarter?\n**Sample Answer:**\n1. The two slips: One was buyer budget held (predictable, I noted it as downside). One was unexpected legal hold-up (not predictable).\n2. I should have flagged the legal risk earlier and escalated when it started.\n3. For the lost deal, the rep could have qualified deeper on why they were losing. For the disqualified deal, we took it too early.\n4. Next quarter: (1) I'm flagging any legal/procurement risk at day 5, not day 14. (2) I'm coaching tighter qualification in Qualification stage before Advanced. (3) I'm updating forecast every week, not just at month-end, so surprises are smaller.\n---\n# PART D: WEEKLY ZOOM DISCUSSION PROMPTS\n**How to Use:** Each week, after that sub-module, pose one of these questions to your cohort. Spend 10 minutes in small groups, then share out. Tie back to the module teaching.\n---\n## Prompt 1 (After Sub-Module 1: Pipeline Architecture)\n**\"What's your team's overall pipeline health? What patterns do you see?\"**\n**Guide:**\n- Have each person describe their pipeline shape (early-stage heavy, stuck, healthy, etc.).\n- Ask: \"If you had to diagnose your pipeline in one sentence, what would you say?\"\n- Identify common patterns in the cohort (e.g., many teams are early-stage heavy).\n- Discuss: \"What would it take to shift from [current] to [healthy]?\"\n**Debrief:**\n- What's one insight you had about your pipeline?\n- What's one coaching conversation you'll have based on this?\n---\n## Prompt 2 (After Sub-Module 2: Conversion Rate)\n**\"How accurate is your forecast? Where are you still guessing?\"**\n**Guide:**\n- Have each person calculate their close rate using Worksheet 2.1 (or share if already done).\n- Ask: \"How surprised are you by your actual rate vs. what you thought it was?\"\n- Ask: \"Are there reps whose rates surprise you (above or below)?\"\n- Discuss: \"If you used this rate to forecast every week, how would it change your accuracy?\"\n**Debrief:**\n- What's your biggest learning about your conversion rate?\n- Which rep do you need to coach, and why?\n---\n## Prompt 3 (After Sub-Module 3: Accurate Forecast)\n**\"What's one stuck deal in your pipeline right now? What's blocking it?\"**\n**Guide:**\n- Have each person name one deal that's been in a stage longer than it should.\n- Ask: \"What's the real reason it's stuck? Is it us or them?\"\n- Ask: \"What's the next move? When will you make it?\"\n- Discuss patterns (rep not pushing, buyer slow, blocker in their org, etc.).\n**Debrief:**\n- What's one action you're taking this week to unstuck a deal?\n- How will you prevent this in the future?\n---\n## Prompt 4 (After Sub-Module 4: Weekly Pipeline Review)\n**\"Which rep is performing below their conversion average? What are you coaching?\"**\n**Guide:**\n- Have each person identify one rep below their team average (or their own average).\n- Ask: \"What's your hypothesis for why?\"\n- Ask: \"What will you ask them to help them see the gap?\"\n- Have cohort offer coaching questions/ideas.\n**Debrief:**\n- What's your coaching conversation plan?\n- When will you have it?\n- How will you follow up?\n---\n## Prompt 5 (After Sub-Module 5: Pipeline Coaching in Practice)\n**\"What's the biggest insight you got from this week's pipeline review?\"**\n**Guide:**\n- Have each person share one thing they learned from their pipeline data.\n- Ask: \"How does this change how you'll manage next week?\"\n- Ask: \"What's one reps behavior you'll celebrate? What's one you'll coach?\"\n- Discuss: \"How is managing by visible metrics different from managing by surprise?\"\n**Debrief:**\n- Commit to one change you'll make in how you lead your team.\n- Share it with the cohort. They hold you accountable.\n---\n# APPENDIX: QUICK REFERENCE TEMPLATES\n## Quick Reference: Forecasting Formula\n```\nFORECAST = (Qualified Pipeline) × (Conversion Rate) + Assessment\nStep 1: Qualified Pipeline\n- Deals in Qualification + Deals in Advanced = $ _______\nStep 2: Conversion Rate\n- Your historical close rate (12 months) = ____%\nStep 3: Base Forecast\n- $ _______ × __% = $ _______\nStep 4: Scenarios\n- Upside (what accelerates): $ _______\n- Downside (what delays): $ _______\n- Forecast Range: $ _______ to $ _______\nStep 5: Confidence\n- Confident in base? ___% (0-100%)\n- Likely to exceed? ___%\n- Likely to miss? ___%\n```\n---\n## Quick Reference: Weekly Review Meeting Agenda\n```\nWEEKLY REVIEW AGENDA (30 min)\n1. Overall Health (3 min) — Pipeline value, on pace?\n2. By Stage (5 min) — Prospect, Discovery, Qual, Advanced\n3. Conversion Rates (4 min) — Team and by rep\n4. At-Risk Deals (4 min) — Stuck deals, past due dates\n5. New/Disqualified (2 min) — Pipeline growth\n6. This Week's Forecast (2 min) — Expected closes\n7. Coaching Moment (5 min) — Rep needing coaching, 1-on-1 scheduled\n```\n---\n## Quick Reference: Five Coaching Gaps\n```\n1. QUALIFICATION GAP: Early-stage heavy → \"How do you decide when to move to Qualification?\"\n2. STUCK DEAL GAP: Deal in stage too long → \"What's the next step? When are you talking to them?\"\n3. CYCLE TIME GAP: Moving too fast or slow → \"How long does [stage] typically take?\"\n4. DEAL SIZE GAP: Too small/large/concentrated → \"What's your typical deal size? Why?\"\n5. CONVERSION RATE GAP: Close rate below average → \"When you lose, what's the reason?\"\n```\n---\n**END OF LEARNER PACK**","rubric":null}],"role_plays":[],"discussion_prompts":[]}}